everruns_sdk/__init__.py
everruns_sdk/auth.py
everruns_sdk/client.py
everruns_sdk/errors.py
everruns_sdk/models.py
everruns_sdk/sse.py
everruns_sdk-0.1.0.dist-info/METADATA
everruns_sdk-0.1.0.dist-info/WHEEL
everruns_sdk-0.1.0.dist-info/RECORD
